[{"schedule_id":1,"name":"MainStreet","minute":"0","hour":"7","day_of_month":"*","month":"*","day_of_week":"*","command":"/usr/bin/curl -X POST \"http://localhost:8086/activatescenes/?id=2\"","description":"","active":0},
{"schedule_id":2,"name":"Tex","minute":"34","hour":"17","day_of_month":"*","month":"*","day_of_week":"*","command":"/usr/bin/curl -X POST \"http://localhost:8086/activatescenes/?id=1\"","description":"","active":0},
{"schedule_id":3,"name":"KillAll","minute":"30","hour":"23","day_of_month":"*","month":"*","day_of_week":"*","command":"/usr/bin/curl -s -X POST \"http://zw2.local/killqueue\" && sleep 2 && /usr/bin/curl -s -X POST \"http://zw2.local//activatescenes/?id=-1\"","description":"","active":0},
{"schedule_id":4,"name":"volume_75","minute":"30","hour":"17","day_of_month":"*","month":"*","day_of_week":"*","command":"/usr/bin/curl -s -X POST \"http://localhost:8086/set_volume\" -H \"Content-Type: application/json\" -d '{\"volume\": 75}'","description":"","active":0},
{"schedule_id":5,"name":"Reboot","minute":"0","hour":"4","day_of_month":"*","month":"*","day_of_week":"0","command":"/usr/bin/sudo /sbin/reboot","description":"","active":0},
{"schedule_id":6,"name":"volume_50","minute":"0","hour":"19","day_of_month":"*","month":"*","day_of_week":"*","command":"/usr/bin/curl -s -X POST \"http://localhost:8086/set_volume\" -H \"Content-Type: application/json\" -d '{\"volume\": 50}'","description":"","active":0}]